LICENSE
Makefile
README.md
build-requirements.txt
requirements.txt
setup.cfg
setup.py
test-requirements.txt
.github/workflows/release.yml
.github/workflows/tests.yml
bbprc/__init__.py
bbprc/arguments.py
bbprc/comment.py
bbprc/main.py
bbprc/readfile.py
bbprc.egg-info/PKG-INFO
bbprc.egg-info/SOURCES.txt
bbprc.egg-info/dependency_links.txt
bbprc.egg-info/entry_points.txt
bbprc.egg-info/not-zip-safe
bbprc.egg-info/pbr.json
bbprc.egg-info/requires.txt
bbprc.egg-info/top_level.txt
tests/file.txt
tests/file_bigger.txt
tests/test_comment.py
tests/test_pr_strings.py