Metadata-Version: 2.1
Name: bbprc
Version: 0.5.2
Summary: Sends comment to BitBucket Pull Requests
Home-page: https://github.com/ITD27M01/bitbucket-pr-commenter
Author: itd27m01
Author-email: igortiunov@gmail.com
License: MIT
Platform: UNKNOWN
Classifier: Programming Language :: Python :: 3
Classifier: Programming Language :: Python :: 3.8
Classifier: License :: OSI Approved :: MIT License
Classifier: Intended Audience :: Developers
Classifier: Operating System :: OS Independent
